{
  "last_updated": "2026-03-22T23:13:57.055368",
  "analysis": {
    "0_league_table": [
      {
        "Team": "Arsenal",
        "P": 31,
        "W": 21,
        "D": 7,
        "L": 3,
        "GF": 61,
        "GA": 22,
        "GD": 39,
        "Pts": 70
      },
      {
        "Team": "Man City",
        "P": 30,
        "W": 18,
        "D": 7,
        "L": 5,
        "GF": 60,
        "GA": 28,
        "GD": 32,
        "Pts": 61
      },
      {
        "Team": "Man United",
        "P": 30,
        "W": 15,
        "D": 9,
        "L": 6,
        "GF": 54,
        "GA": 41,
        "GD": 13,
        "Pts": 54
      },
      {
        "Team": "Aston Villa",
        "P": 30,
        "W": 15,
        "D": 6,
        "L": 9,
        "GF": 40,
        "GA": 37,
        "GD": 3,
        "Pts": 51
      },
      {
        "Team": "Liverpool",
        "P": 30,
        "W": 14,
        "D": 7,
        "L": 9,
        "GF": 49,
        "GA": 40,
        "GD": 9,
        "Pts": 49
      },
      {
        "Team": "Chelsea",
        "P": 30,
        "W": 13,
        "D": 9,
        "L": 8,
        "GF": 53,
        "GA": 35,
        "GD": 18,
        "Pts": 48
      },
      {
        "Team": "Brentford",
        "P": 30,
        "W": 13,
        "D": 6,
        "L": 11,
        "GF": 46,
        "GA": 42,
        "GD": 4,
        "Pts": 45
      },
      {
        "Team": "Everton",
        "P": 30,
        "W": 12,
        "D": 7,
        "L": 11,
        "GF": 34,
        "GA": 35,
        "GD": -1,
        "Pts": 43
      },
      {
        "Team": "Newcastle",
        "P": 30,
        "W": 12,
        "D": 6,
        "L": 12,
        "GF": 43,
        "GA": 43,
        "GD": 0,
        "Pts": 42
      },
      {
        "Team": "Bournemouth",
        "P": 30,
        "W": 9,
        "D": 14,
        "L": 7,
        "GF": 44,
        "GA": 46,
        "GD": -2,
        "Pts": 41
      },
      {
        "Team": "Fulham",
        "P": 30,
        "W": 12,
        "D": 5,
        "L": 13,
        "GF": 40,
        "GA": 43,
        "GD": -3,
        "Pts": 41
      },
      {
        "Team": "Brighton",
        "P": 30,
        "W": 10,
        "D": 10,
        "L": 10,
        "GF": 39,
        "GA": 36,
        "GD": 3,
        "Pts": 40
      },
      {
        "Team": "Sunderland",
        "P": 30,
        "W": 10,
        "D": 10,
        "L": 10,
        "GF": 30,
        "GA": 35,
        "GD": -5,
        "Pts": 40
      },
      {
        "Team": "Crystal Palace",
        "P": 30,
        "W": 10,
        "D": 9,
        "L": 11,
        "GF": 33,
        "GA": 35,
        "GD": -2,
        "Pts": 39
      },
      {
        "Team": "Leeds",
        "P": 30,
        "W": 7,
        "D": 11,
        "L": 12,
        "GF": 37,
        "GA": 48,
        "GD": -11,
        "Pts": 32
      },
      {
        "Team": "Tottenham",
        "P": 30,
        "W": 7,
        "D": 9,
        "L": 14,
        "GF": 40,
        "GA": 47,
        "GD": -7,
        "Pts": 30
      },
      {
        "Team": "Nott'm Forest",
        "P": 30,
        "W": 7,
        "D": 8,
        "L": 15,
        "GF": 28,
        "GA": 43,
        "GD": -15,
        "Pts": 29
      },
      {
        "Team": "West Ham",
        "P": 30,
        "W": 7,
        "D": 8,
        "L": 15,
        "GF": 36,
        "GA": 55,
        "GD": -19,
        "Pts": 29
      },
      {
        "Team": "Burnley",
        "P": 30,
        "W": 4,
        "D": 8,
        "L": 18,
        "GF": 32,
        "GA": 58,
        "GD": -26,
        "Pts": 20
      },
      {
        "Team": "Wolves",
        "P": 31,
        "W": 3,
        "D": 8,
        "L": 20,
        "GF": 24,
        "GA": 54,
        "GD": -30,
        "Pts": 17
      }
    ],
    "1_team_efficiency": [
      {
        "HomeTeam": "Arsenal",
        "Goals": 61,
        "SOT": 153,
        "Clinical_Rate": 0.399
      },
      {
        "HomeTeam": "Brentford",
        "Goals": 46,
        "SOT": 120,
        "Clinical_Rate": 0.383
      },
      {
        "HomeTeam": "Man City",
        "Goals": 60,
        "SOT": 157,
        "Clinical_Rate": 0.382
      },
      {
        "HomeTeam": "Chelsea",
        "Goals": 53,
        "SOT": 141,
        "Clinical_Rate": 0.376
      },
      {
        "HomeTeam": "Fulham",
        "Goals": 40,
        "SOT": 108,
        "Clinical_Rate": 0.37
      },
      {
        "HomeTeam": "Burnley",
        "Goals": 32,
        "SOT": 87,
        "Clinical_Rate": 0.368
      },
      {
        "HomeTeam": "Liverpool",
        "Goals": 49,
        "SOT": 135,
        "Clinical_Rate": 0.363
      },
      {
        "HomeTeam": "West Ham",
        "Goals": 36,
        "SOT": 103,
        "Clinical_Rate": 0.35
      },
      {
        "HomeTeam": "Tottenham",
        "Goals": 40,
        "SOT": 115,
        "Clinical_Rate": 0.348
      },
      {
        "HomeTeam": "Everton",
        "Goals": 34,
        "SOT": 102,
        "Clinical_Rate": 0.333
      },
      {
        "HomeTeam": "Leeds",
        "Goals": 37,
        "SOT": 116,
        "Clinical_Rate": 0.319
      },
      {
        "HomeTeam": "Sunderland",
        "Goals": 30,
        "SOT": 95,
        "Clinical_Rate": 0.316
      },
      {
        "HomeTeam": "Man United",
        "Goals": 54,
        "SOT": 173,
        "Clinical_Rate": 0.312
      },
      {
        "HomeTeam": "Aston Villa",
        "Goals": 40,
        "SOT": 128,
        "Clinical_Rate": 0.312
      },
      {
        "HomeTeam": "Bournemouth",
        "Goals": 44,
        "SOT": 144,
        "Clinical_Rate": 0.306
      },
      {
        "HomeTeam": "Crystal Palace",
        "Goals": 33,
        "SOT": 109,
        "Clinical_Rate": 0.303
      },
      {
        "HomeTeam": "Newcastle",
        "Goals": 43,
        "SOT": 142,
        "Clinical_Rate": 0.303
      },
      {
        "HomeTeam": "Brighton",
        "Goals": 39,
        "SOT": 131,
        "Clinical_Rate": 0.298
      },
      {
        "HomeTeam": "Nott'm Forest",
        "Goals": 28,
        "SOT": 116,
        "Clinical_Rate": 0.241
      },
      {
        "HomeTeam": "Wolves",
        "Goals": 24,
        "SOT": 101,
        "Clinical_Rate": 0.238
      }
    ],
    "2_referee_discipline": [
      {
        "Referee": "S Attwell",
        "Matches": 19,
        "AvgCards": 4.684210526315789
      },
      {
        "Referee": "M Salisbury",
        "Matches": 10,
        "AvgCards": 4.5
      },
      {
        "Referee": "R Jones",
        "Matches": 15,
        "AvgCards": 4.2
      },
      {
        "Referee": "S Hooper",
        "Matches": 15,
        "AvgCards": 4.133333333333334
      },
      {
        "Referee": "T Robinson",
        "Matches": 9,
        "AvgCards": 4.111111111111111
      },
      {
        "Referee": "J Brooks",
        "Matches": 10,
        "AvgCards": 4.1
      },
      {
        "Referee": "D England",
        "Matches": 18,
        "AvgCards": 4.055555555555555
      },
      {
        "Referee": "T Bramall",
        "Matches": 18,
        "AvgCards": 4.055555555555555
      },
      {
        "Referee": "P Bankes",
        "Matches": 22,
        "AvgCards": 4.0
      },
      {
        "Referee": "A Taylor",
        "Matches": 23,
        "AvgCards": 3.9565217391304346
      },
      {
        "Referee": "P Tierney",
        "Matches": 6,
        "AvgCards": 3.8333333333333335
      },
      {
        "Referee": "J Gillett",
        "Matches": 17,
        "AvgCards": 3.823529411764706
      },
      {
        "Referee": "S Barrott",
        "Matches": 18,
        "AvgCards": 3.7777777777777777
      },
      {
        "Referee": "C Kavanagh",
        "Matches": 22,
        "AvgCards": 3.772727272727273
      },
      {
        "Referee": "A Madley",
        "Matches": 16,
        "AvgCards": 3.5
      },
      {
        "Referee": "T Harrington",
        "Matches": 11,
        "AvgCards": 3.090909090909091
      },
      {
        "Referee": "M Oliver",
        "Matches": 22,
        "AvgCards": 2.909090909090909
      },
      {
        "Referee": "C Pawson",
        "Matches": 17,
        "AvgCards": 2.588235294117647
      }
    ],
    "3_home_advantage": {
      "home_win_pct": 41.5,
      "away_win_pct": 31.2,
      "draw_pct": 27.2
    },
    "4_comeback_kings": [
      {
        "Team": "Brighton",
        "count": 3
      },
      {
        "Team": "Aston Villa",
        "count": 3
      },
      {
        "Team": "Everton",
        "count": 2
      },
      {
        "Team": "Man United",
        "count": 2
      },
      {
        "Team": "Brentford",
        "count": 1
      },
      {
        "Team": "Sunderland",
        "count": 1
      },
      {
        "Team": "Newcastle",
        "count": 1
      },
      {
        "Team": "Fulham",
        "count": 1
      },
      {
        "Team": "Chelsea",
        "count": 1
      },
      {
        "Team": "Arsenal",
        "count": 1
      },
      {
        "Team": "Nott'm Forest",
        "count": 1
      },
      {
        "Team": "Bournemouth",
        "count": 1
      }
    ],
    "5_betting_accuracy": {
      "favorite_win_rate": 49.5
    },
    "6_clean_sheets": [
      {
        "HomeTeam": "Arsenal",
        "count": 15.0
      },
      {
        "HomeTeam": "Man City",
        "count": 12.0
      },
      {
        "HomeTeam": "Crystal Palace",
        "count": 11.0
      },
      {
        "HomeTeam": "Everton",
        "count": 10.0
      },
      {
        "HomeTeam": "Sunderland",
        "count": 9.0
      },
      {
        "HomeTeam": "Chelsea",
        "count": 9.0
      },
      {
        "HomeTeam": "Bournemouth",
        "count": 9.0
      },
      {
        "HomeTeam": "Liverpool",
        "count": 9.0
      },
      {
        "HomeTeam": "Newcastle",
        "count": 8.0
      },
      {
        "HomeTeam": "Aston Villa",
        "count": 8.0
      },
      {
        "HomeTeam": "Brentford",
        "count": 7.0
      },
      {
        "HomeTeam": "Brighton",
        "count": 7.0
      },
      {
        "HomeTeam": "Tottenham",
        "count": 7.0
      },
      {
        "HomeTeam": "Nott'm Forest",
        "count": 7.0
      },
      {
        "HomeTeam": "Fulham",
        "count": 6.0
      },
      {
        "HomeTeam": "Leeds",
        "count": 5.0
      },
      {
        "HomeTeam": "Man United",
        "count": 5.0
      },
      {
        "HomeTeam": "Burnley",
        "count": 4.0
      },
      {
        "HomeTeam": "West Ham",
        "count": 4.0
      },
      {
        "HomeTeam": "Wolves",
        "count": 4.0
      }
    ],
    "7_second_half_specialists": [
      {
        "HomeTeam": "Arsenal",
        "Goals_1H": 22,
        "Goals_2H": 39,
        "2H_Increase": 17
      },
      {
        "HomeTeam": "Liverpool",
        "Goals_1H": 17,
        "Goals_2H": 32,
        "2H_Increase": 15
      },
      {
        "HomeTeam": "Man United",
        "Goals_1H": 21,
        "Goals_2H": 33,
        "2H_Increase": 12
      },
      {
        "HomeTeam": "Brighton",
        "Goals_1H": 14,
        "Goals_2H": 25,
        "2H_Increase": 11
      },
      {
        "HomeTeam": "Sunderland",
        "Goals_1H": 10,
        "Goals_2H": 20,
        "2H_Increase": 10
      },
      {
        "HomeTeam": "Fulham",
        "Goals_1H": 15,
        "Goals_2H": 25,
        "2H_Increase": 10
      },
      {
        "HomeTeam": "Aston Villa",
        "Goals_1H": 15,
        "Goals_2H": 25,
        "2H_Increase": 10
      },
      {
        "HomeTeam": "Tottenham",
        "Goals_1H": 16,
        "Goals_2H": 24,
        "2H_Increase": 8
      },
      {
        "HomeTeam": "Nott'm Forest",
        "Goals_1H": 10,
        "Goals_2H": 18,
        "2H_Increase": 8
      },
      {
        "HomeTeam": "Chelsea",
        "Goals_1H": 24,
        "Goals_2H": 29,
        "2H_Increase": 5
      },
      {
        "HomeTeam": "Burnley",
        "Goals_1H": 14,
        "Goals_2H": 18,
        "2H_Increase": 4
      },
      {
        "HomeTeam": "Brentford",
        "Goals_1H": 21,
        "Goals_2H": 25,
        "2H_Increase": 4
      },
      {
        "HomeTeam": "Everton",
        "Goals_1H": 15,
        "Goals_2H": 19,
        "2H_Increase": 4
      },
      {
        "HomeTeam": "Bournemouth",
        "Goals_1H": 21,
        "Goals_2H": 23,
        "2H_Increase": 2
      },
      {
        "HomeTeam": "Wolves",
        "Goals_1H": 11,
        "Goals_2H": 13,
        "2H_Increase": 2
      },
      {
        "HomeTeam": "Leeds",
        "Goals_1H": 19,
        "Goals_2H": 18,
        "2H_Increase": -1
      },
      {
        "HomeTeam": "Newcastle",
        "Goals_1H": 22,
        "Goals_2H": 21,
        "2H_Increase": -1
      },
      {
        "HomeTeam": "Crystal Palace",
        "Goals_1H": 18,
        "Goals_2H": 15,
        "2H_Increase": -3
      },
      {
        "HomeTeam": "West Ham",
        "Goals_1H": 20,
        "Goals_2H": 16,
        "2H_Increase": -4
      },
      {
        "HomeTeam": "Man City",
        "Goals_1H": 35,
        "Goals_2H": 25,
        "2H_Increase": -10
      }
    ],
    "8_corner_conversion": [
      {
        "HomeTeam": "Man United",
        "Corners": 134,
        "Goals": 54,
        "Goals_per_Corner": 0.403
      },
      {
        "HomeTeam": "Man City",
        "Corners": 173,
        "Goals": 60,
        "Goals_per_Corner": 0.3468
      },
      {
        "HomeTeam": "Arsenal",
        "Corners": 181,
        "Goals": 61,
        "Goals_per_Corner": 0.337
      },
      {
        "HomeTeam": "Brentford",
        "Corners": 146,
        "Goals": 46,
        "Goals_per_Corner": 0.3151
      },
      {
        "HomeTeam": "Burnley",
        "Corners": 105,
        "Goals": 32,
        "Goals_per_Corner": 0.3048
      },
      {
        "HomeTeam": "Chelsea",
        "Corners": 184,
        "Goals": 53,
        "Goals_per_Corner": 0.288
      },
      {
        "HomeTeam": "Fulham",
        "Corners": 141,
        "Goals": 40,
        "Goals_per_Corner": 0.2837
      },
      {
        "HomeTeam": "Sunderland",
        "Corners": 107,
        "Goals": 30,
        "Goals_per_Corner": 0.2804
      },
      {
        "HomeTeam": "Liverpool",
        "Corners": 177,
        "Goals": 49,
        "Goals_per_Corner": 0.2768
      },
      {
        "HomeTeam": "Leeds",
        "Corners": 134,
        "Goals": 37,
        "Goals_per_Corner": 0.2761
      },
      {
        "HomeTeam": "Brighton",
        "Corners": 143,
        "Goals": 39,
        "Goals_per_Corner": 0.2727
      },
      {
        "HomeTeam": "Tottenham",
        "Corners": 148,
        "Goals": 40,
        "Goals_per_Corner": 0.2703
      },
      {
        "HomeTeam": "Everton",
        "Corners": 132,
        "Goals": 34,
        "Goals_per_Corner": 0.2576
      },
      {
        "HomeTeam": "Bournemouth",
        "Corners": 171,
        "Goals": 44,
        "Goals_per_Corner": 0.2573
      },
      {
        "HomeTeam": "Crystal Palace",
        "Corners": 129,
        "Goals": 33,
        "Goals_per_Corner": 0.2558
      },
      {
        "HomeTeam": "Aston Villa",
        "Corners": 160,
        "Goals": 40,
        "Goals_per_Corner": 0.25
      },
      {
        "HomeTeam": "West Ham",
        "Corners": 150,
        "Goals": 36,
        "Goals_per_Corner": 0.24
      },
      {
        "HomeTeam": "Wolves",
        "Corners": 100,
        "Goals": 24,
        "Goals_per_Corner": 0.24
      },
      {
        "HomeTeam": "Newcastle",
        "Corners": 196,
        "Goals": 43,
        "Goals_per_Corner": 0.2194
      },
      {
        "HomeTeam": "Nott'm Forest",
        "Corners": 164,
        "Goals": 28,
        "Goals_per_Corner": 0.1707
      }
    ],
    "9_aggression_vs_success": {
      "correlation": -0.466,
      "data": [
        {
          "HomeTeam": "Arsenal",
          "Fouls": 316,
          "Points": 70
        },
        {
          "HomeTeam": "Man City",
          "Fouls": 298,
          "Points": 61
        },
        {
          "HomeTeam": "Man United",
          "Fouls": 308,
          "Points": 54
        },
        {
          "HomeTeam": "Aston Villa",
          "Fouls": 307,
          "Points": 51
        },
        {
          "HomeTeam": "Liverpool",
          "Fouls": 294,
          "Points": 49
        },
        {
          "HomeTeam": "Chelsea",
          "Fouls": 333,
          "Points": 48
        },
        {
          "HomeTeam": "Brentford",
          "Fouls": 320,
          "Points": 45
        },
        {
          "HomeTeam": "Everton",
          "Fouls": 319,
          "Points": 43
        },
        {
          "HomeTeam": "Newcastle",
          "Fouls": 310,
          "Points": 42
        },
        {
          "HomeTeam": "Bournemouth",
          "Fouls": 357,
          "Points": 41
        },
        {
          "HomeTeam": "Fulham",
          "Fouls": 332,
          "Points": 41
        },
        {
          "HomeTeam": "Brighton",
          "Fouls": 363,
          "Points": 40
        },
        {
          "HomeTeam": "Sunderland",
          "Fouls": 303,
          "Points": 40
        },
        {
          "HomeTeam": "Crystal Palace",
          "Fouls": 321,
          "Points": 39
        },
        {
          "HomeTeam": "Leeds",
          "Fouls": 316,
          "Points": 32
        },
        {
          "HomeTeam": "Tottenham",
          "Fouls": 350,
          "Points": 30
        },
        {
          "HomeTeam": "West Ham",
          "Fouls": 334,
          "Points": 29
        },
        {
          "HomeTeam": "Nott'm Forest",
          "Fouls": 314,
          "Points": 29
        },
        {
          "HomeTeam": "Burnley",
          "Fouls": 301,
          "Points": 20
        },
        {
          "HomeTeam": "Wolves",
          "Fouls": 409,
          "Points": 17
        }
      ]
    },
    "10_home_away_split": [
      {
        "Team": "Wolves",
        "HomePts": 12,
        "AwayPts": 5,
        "TotalPts": 17,
        "Home_Contribution_%": 70.6
      },
      {
        "Team": "Leeds",
        "HomePts": 22,
        "AwayPts": 10,
        "TotalPts": 32,
        "Home_Contribution_%": 68.8
      },
      {
        "Team": "Sunderland",
        "HomePts": 26,
        "AwayPts": 14,
        "TotalPts": 40,
        "Home_Contribution_%": 65.0
      },
      {
        "Team": "Fulham",
        "HomePts": 26,
        "AwayPts": 15,
        "TotalPts": 41,
        "Home_Contribution_%": 63.4
      },
      {
        "Team": "Newcastle",
        "HomePts": 26,
        "AwayPts": 16,
        "TotalPts": 42,
        "Home_Contribution_%": 61.9
      },
      {
        "Team": "Man United",
        "HomePts": 33,
        "AwayPts": 21,
        "TotalPts": 54,
        "Home_Contribution_%": 61.1
      },
      {
        "Team": "Bournemouth",
        "HomePts": 25,
        "AwayPts": 16,
        "TotalPts": 41,
        "Home_Contribution_%": 61.0
      },
      {
        "Team": "Brighton",
        "HomePts": 24,
        "AwayPts": 16,
        "TotalPts": 40,
        "Home_Contribution_%": 60.0
      },
      {
        "Team": "Man City",
        "HomePts": 36,
        "AwayPts": 25,
        "TotalPts": 61,
        "Home_Contribution_%": 59.0
      },
      {
        "Team": "Brentford",
        "HomePts": 26,
        "AwayPts": 19,
        "TotalPts": 45,
        "Home_Contribution_%": 57.8
      },
      {
        "Team": "Liverpool",
        "HomePts": 28,
        "AwayPts": 21,
        "TotalPts": 49,
        "Home_Contribution_%": 57.1
      },
      {
        "Team": "Aston Villa",
        "HomePts": 29,
        "AwayPts": 22,
        "TotalPts": 51,
        "Home_Contribution_%": 56.9
      },
      {
        "Team": "Burnley",
        "HomePts": 11,
        "AwayPts": 9,
        "TotalPts": 20,
        "Home_Contribution_%": 55.0
      },
      {
        "Team": "Arsenal",
        "HomePts": 38,
        "AwayPts": 32,
        "TotalPts": 70,
        "Home_Contribution_%": 54.3
      },
      {
        "Team": "Nott'm Forest",
        "HomePts": 14,
        "AwayPts": 15,
        "TotalPts": 29,
        "Home_Contribution_%": 48.3
      },
      {
        "Team": "Chelsea",
        "HomePts": 23,
        "AwayPts": 25,
        "TotalPts": 48,
        "Home_Contribution_%": 47.9
      },
      {
        "Team": "West Ham",
        "HomePts": 13,
        "AwayPts": 16,
        "TotalPts": 29,
        "Home_Contribution_%": 44.8
      },
      {
        "Team": "Everton",
        "HomePts": 19,
        "AwayPts": 24,
        "TotalPts": 43,
        "Home_Contribution_%": 44.2
      },
      {
        "Team": "Crystal Palace",
        "HomePts": 16,
        "AwayPts": 23,
        "TotalPts": 39,
        "Home_Contribution_%": 41.0
      },
      {
        "Team": "Tottenham",
        "HomePts": 10,
        "AwayPts": 20,
        "TotalPts": 30,
        "Home_Contribution_%": 33.3
      }
    ],
    "11_entertainment_factor": [
      {
        "HomeTeam": "Tottenham",
        "sum": 20,
        "count": 30,
        "Over25_Rate_%": 66.7
      },
      {
        "HomeTeam": "Chelsea",
        "sum": 19,
        "count": 30,
        "Over25_Rate_%": 63.3
      },
      {
        "HomeTeam": "Newcastle",
        "sum": 19,
        "count": 30,
        "Over25_Rate_%": 63.3
      },
      {
        "HomeTeam": "Liverpool",
        "sum": 18,
        "count": 30,
        "Over25_Rate_%": 60.0
      },
      {
        "HomeTeam": "Man City",
        "sum": 18,
        "count": 30,
        "Over25_Rate_%": 60.0
      },
      {
        "HomeTeam": "Man United",
        "sum": 18,
        "count": 30,
        "Over25_Rate_%": 60.0
      },
      {
        "HomeTeam": "West Ham",
        "sum": 18,
        "count": 30,
        "Over25_Rate_%": 60.0
      },
      {
        "HomeTeam": "Fulham",
        "sum": 17,
        "count": 30,
        "Over25_Rate_%": 56.7
      },
      {
        "HomeTeam": "Leeds",
        "sum": 16,
        "count": 30,
        "Over25_Rate_%": 53.3
      },
      {
        "HomeTeam": "Bournemouth",
        "sum": 16,
        "count": 30,
        "Over25_Rate_%": 53.3
      },
      {
        "HomeTeam": "Arsenal",
        "sum": 16,
        "count": 31,
        "Over25_Rate_%": 51.6
      },
      {
        "HomeTeam": "Aston Villa",
        "sum": 15,
        "count": 30,
        "Over25_Rate_%": 50.0
      },
      {
        "HomeTeam": "Brentford",
        "sum": 15,
        "count": 30,
        "Over25_Rate_%": 50.0
      },
      {
        "HomeTeam": "Nott'm Forest",
        "sum": 15,
        "count": 30,
        "Over25_Rate_%": 50.0
      },
      {
        "HomeTeam": "Burnley",
        "sum": 15,
        "count": 30,
        "Over25_Rate_%": 50.0
      },
      {
        "HomeTeam": "Crystal Palace",
        "sum": 14,
        "count": 30,
        "Over25_Rate_%": 46.7
      },
      {
        "HomeTeam": "Wolves",
        "sum": 14,
        "count": 31,
        "Over25_Rate_%": 45.2
      },
      {
        "HomeTeam": "Brighton",
        "sum": 13,
        "count": 30,
        "Over25_Rate_%": 43.3
      },
      {
        "HomeTeam": "Sunderland",
        "sum": 12,
        "count": 30,
        "Over25_Rate_%": 40.0
      },
      {
        "HomeTeam": "Everton",
        "sum": 10,
        "count": 30,
        "Over25_Rate_%": 33.3
      }
    ],
    "12_shot_quality": [
      {
        "HomeTeam": "Brentford",
        "HST": 120,
        "HS": 314,
        "Accuracy_%": 38.2
      },
      {
        "HomeTeam": "Man United",
        "HST": 173,
        "HS": 478,
        "Accuracy_%": 36.2
      },
      {
        "HomeTeam": "Newcastle",
        "HST": 142,
        "HS": 393,
        "Accuracy_%": 36.1
      },
      {
        "HomeTeam": "Man City",
        "HST": 157,
        "HS": 443,
        "Accuracy_%": 35.4
      },
      {
        "HomeTeam": "Wolves",
        "HST": 101,
        "HS": 286,
        "Accuracy_%": 35.3
      },
      {
        "HomeTeam": "Tottenham",
        "HST": 115,
        "HS": 331,
        "Accuracy_%": 34.7
      },
      {
        "HomeTeam": "Bournemouth",
        "HST": 144,
        "HS": 419,
        "Accuracy_%": 34.4
      },
      {
        "HomeTeam": "Brighton",
        "HST": 131,
        "HS": 382,
        "Accuracy_%": 34.3
      },
      {
        "HomeTeam": "Aston Villa",
        "HST": 128,
        "HS": 374,
        "Accuracy_%": 34.2
      },
      {
        "HomeTeam": "Chelsea",
        "HST": 141,
        "HS": 414,
        "Accuracy_%": 34.1
      },
      {
        "HomeTeam": "West Ham",
        "HST": 103,
        "HS": 305,
        "Accuracy_%": 33.8
      },
      {
        "HomeTeam": "Arsenal",
        "HST": 153,
        "HS": 454,
        "Accuracy_%": 33.7
      },
      {
        "HomeTeam": "Sunderland",
        "HST": 95,
        "HS": 289,
        "Accuracy_%": 32.9
      },
      {
        "HomeTeam": "Burnley",
        "HST": 87,
        "HS": 278,
        "Accuracy_%": 31.3
      },
      {
        "HomeTeam": "Crystal Palace",
        "HST": 109,
        "HS": 350,
        "Accuracy_%": 31.1
      },
      {
        "HomeTeam": "Leeds",
        "HST": 116,
        "HS": 373,
        "Accuracy_%": 31.1
      },
      {
        "HomeTeam": "Everton",
        "HST": 102,
        "HS": 330,
        "Accuracy_%": 30.9
      },
      {
        "HomeTeam": "Fulham",
        "HST": 108,
        "HS": 358,
        "Accuracy_%": 30.2
      },
      {
        "HomeTeam": "Nott'm Forest",
        "HST": 116,
        "HS": 384,
        "Accuracy_%": 30.2
      },
      {
        "HomeTeam": "Liverpool",
        "HST": 135,
        "HS": 474,
        "Accuracy_%": 28.5
      }
    ],
    "13_reputation_index": [
      {
        "HomeTeam": "Tottenham",
        "HY": 74,
        "HF": 350,
        "CardsPer100Fouls": 21.1
      },
      {
        "HomeTeam": "Chelsea",
        "HY": 69,
        "HF": 333,
        "CardsPer100Fouls": 20.7
      },
      {
        "HomeTeam": "Brighton",
        "HY": 74,
        "HF": 363,
        "CardsPer100Fouls": 20.4
      },
      {
        "HomeTeam": "Sunderland",
        "HY": 59,
        "HF": 303,
        "CardsPer100Fouls": 19.5
      },
      {
        "HomeTeam": "Crystal Palace",
        "HY": 62,
        "HF": 321,
        "CardsPer100Fouls": 19.3
      },
      {
        "HomeTeam": "Bournemouth",
        "HY": 69,
        "HF": 357,
        "CardsPer100Fouls": 19.3
      },
      {
        "HomeTeam": "Fulham",
        "HY": 63,
        "HF": 332,
        "CardsPer100Fouls": 19.0
      },
      {
        "HomeTeam": "Man City",
        "HY": 56,
        "HF": 298,
        "CardsPer100Fouls": 18.8
      },
      {
        "HomeTeam": "Brentford",
        "HY": 58,
        "HF": 320,
        "CardsPer100Fouls": 18.1
      },
      {
        "HomeTeam": "Everton",
        "HY": 53,
        "HF": 319,
        "CardsPer100Fouls": 16.6
      },
      {
        "HomeTeam": "Wolves",
        "HY": 67,
        "HF": 409,
        "CardsPer100Fouls": 16.4
      },
      {
        "HomeTeam": "Burnley",
        "HY": 49,
        "HF": 301,
        "CardsPer100Fouls": 16.3
      },
      {
        "HomeTeam": "Newcastle",
        "HY": 49,
        "HF": 310,
        "CardsPer100Fouls": 15.8
      },
      {
        "HomeTeam": "Aston Villa",
        "HY": 47,
        "HF": 307,
        "CardsPer100Fouls": 15.3
      },
      {
        "HomeTeam": "West Ham",
        "HY": 51,
        "HF": 334,
        "CardsPer100Fouls": 15.3
      },
      {
        "HomeTeam": "Liverpool",
        "HY": 44,
        "HF": 294,
        "CardsPer100Fouls": 15.0
      },
      {
        "HomeTeam": "Leeds",
        "HY": 47,
        "HF": 316,
        "CardsPer100Fouls": 14.9
      },
      {
        "HomeTeam": "Nott'm Forest",
        "HY": 46,
        "HF": 314,
        "CardsPer100Fouls": 14.6
      },
      {
        "HomeTeam": "Man United",
        "HY": 44,
        "HF": 308,
        "CardsPer100Fouls": 14.3
      },
      {
        "HomeTeam": "Arsenal",
        "HY": 40,
        "HF": 316,
        "CardsPer100Fouls": 12.7
      }
    ],
    "14_referee_bias": [
      {
        "Referee": "J Brooks",
        "Matches": 10,
        "HomeWinRate": 70.0,
        "AvgAwayCardBias": 0.4
      },
      {
        "Referee": "P Bankes",
        "Matches": 22,
        "HomeWinRate": 68.18181818181817,
        "AvgAwayCardBias": 0.8181818181818182
      },
      {
        "Referee": "T Robinson",
        "Matches": 9,
        "HomeWinRate": 55.55555555555556,
        "AvgAwayCardBias": 1.3333333333333333
      },
      {
        "Referee": "R Jones",
        "Matches": 15,
        "HomeWinRate": 53.333333333333336,
        "AvgAwayCardBias": 0.2
      },
      {
        "Referee": "M Salisbury",
        "Matches": 10,
        "HomeWinRate": 50.0,
        "AvgAwayCardBias": 0.3
      },
      {
        "Referee": "P Tierney",
        "Matches": 6,
        "HomeWinRate": 50.0,
        "AvgAwayCardBias": 0.16666666666666666
      },
      {
        "Referee": "A Taylor",
        "Matches": 23,
        "HomeWinRate": 47.82608695652174,
        "AvgAwayCardBias": 0.21739130434782608
      },
      {
        "Referee": "C Kavanagh",
        "Matches": 22,
        "HomeWinRate": 45.45454545454545,
        "AvgAwayCardBias": 0.5909090909090909
      },
      {
        "Referee": "T Bramall",
        "Matches": 18,
        "HomeWinRate": 44.44444444444444,
        "AvgAwayCardBias": 0.9444444444444444
      },
      {
        "Referee": "D England",
        "Matches": 18,
        "HomeWinRate": 44.44444444444444,
        "AvgAwayCardBias": 0.2222222222222222
      }
    ],
    "15_betting_roi": [
      {
        "Bookmaker": "Market Avg (Opening)",
        "Fav_ROI": -8.75,
        "Underdog_ROI": -17.14
      },
      {
        "Bookmaker": "Market Avg (Closing)",
        "Fav_ROI": -6.27,
        "Underdog_ROI": -16.01
      },
      {
        "Bookmaker": "Bet365 (Opening)",
        "Fav_ROI": -9.5,
        "Underdog_ROI": -14.11
      },
      {
        "Bookmaker": "Bet365 (Closing)",
        "Fav_ROI": -6.57,
        "Underdog_ROI": -17.73
      },
      {
        "Bookmaker": "Betfair (Opening)",
        "Fav_ROI": -9.52,
        "Underdog_ROI": -15.06
      },
      {
        "Bookmaker": "Betfair (Closing)",
        "Fav_ROI": -6.15,
        "Underdog_ROI": -20.2
      },
      {
        "Bookmaker": "Betfair Exchange (Opening)",
        "Fav_ROI": -5.17,
        "Underdog_ROI": -7.97
      },
      {
        "Bookmaker": "Betfair Exchange (Closing)",
        "Fav_ROI": -3.7,
        "Underdog_ROI": -11.06
      },
      {
        "Bookmaker": "BetMGM (Opening)",
        "Fav_ROI": -6.71,
        "Underdog_ROI": -10.85
      },
      {
        "Bookmaker": "BetMGM (Closing)",
        "Fav_ROI": -6.05,
        "Underdog_ROI": -11.69
      },
      {
        "Bookmaker": "BetVictor (Opening)",
        "Fav_ROI": -9.45,
        "Underdog_ROI": -17.75
      },
      {
        "Bookmaker": "BetVictor (Closing)",
        "Fav_ROI": -6.77,
        "Underdog_ROI": -14.49
      },
      {
        "Bookmaker": "Bwin (Opening)",
        "Fav_ROI": -7.76,
        "Underdog_ROI": -15.1
      },
      {
        "Bookmaker": "Bwin (Closing)",
        "Fav_ROI": -5.3,
        "Underdog_ROI": -21.34
      },
      {
        "Bookmaker": "Cloudbet (Opening)",
        "Fav_ROI": -4.19,
        "Underdog_ROI": -17.66
      },
      {
        "Bookmaker": "Cloudbet (Closing)",
        "Fav_ROI": -2.26,
        "Underdog_ROI": -23.03
      },
      {
        "Bookmaker": "Ladbrokes (Opening)",
        "Fav_ROI": -4.68,
        "Underdog_ROI": -22.38
      },
      {
        "Bookmaker": "Ladbrokes (Closing)",
        "Fav_ROI": -2.7,
        "Underdog_ROI": -19.79
      },
      {
        "Bookmaker": "Market Max (Opening)",
        "Fav_ROI": -7.43,
        "Underdog_ROI": -11.37
      },
      {
        "Bookmaker": "Market Max (Closing)",
        "Fav_ROI": -3.71,
        "Underdog_ROI": -16.41
      },
      {
        "Bookmaker": "Pinnacle (Opening)",
        "Fav_ROI": -2.3,
        "Underdog_ROI": -5.19
      },
      {
        "Bookmaker": "Pinnacle (Closing)",
        "Fav_ROI": -3.33,
        "Underdog_ROI": -17.42
      }
    ],
    "16_defensive_wall": [
      {
        "HomeTeam": "Sunderland",
        "SOT_Conc": 130,
        "G_Conc": 35,
        "SOT_per_Goal": 3.71
      },
      {
        "HomeTeam": "Man City",
        "SOT_Conc": 103,
        "G_Conc": 28,
        "SOT_per_Goal": 3.68
      },
      {
        "HomeTeam": "Crystal Palace",
        "SOT_Conc": 127,
        "G_Conc": 35,
        "SOT_per_Goal": 3.63
      },
      {
        "HomeTeam": "Aston Villa",
        "SOT_Conc": 131,
        "G_Conc": 37,
        "SOT_per_Goal": 3.54
      },
      {
        "HomeTeam": "Everton",
        "SOT_Conc": 124,
        "G_Conc": 35,
        "SOT_per_Goal": 3.54
      },
      {
        "HomeTeam": "Chelsea",
        "SOT_Conc": 117,
        "G_Conc": 35,
        "SOT_per_Goal": 3.34
      },
      {
        "HomeTeam": "Arsenal",
        "SOT_Conc": 72,
        "G_Conc": 22,
        "SOT_per_Goal": 3.27
      },
      {
        "HomeTeam": "Brighton",
        "SOT_Conc": 117,
        "G_Conc": 36,
        "SOT_per_Goal": 3.25
      },
      {
        "HomeTeam": "Bournemouth",
        "SOT_Conc": 135,
        "G_Conc": 46,
        "SOT_per_Goal": 2.93
      },
      {
        "HomeTeam": "Newcastle",
        "SOT_Conc": 125,
        "G_Conc": 43,
        "SOT_per_Goal": 2.91
      },
      {
        "HomeTeam": "Burnley",
        "SOT_Conc": 169,
        "G_Conc": 58,
        "SOT_per_Goal": 2.91
      },
      {
        "HomeTeam": "West Ham",
        "SOT_Conc": 160,
        "G_Conc": 55,
        "SOT_per_Goal": 2.91
      },
      {
        "HomeTeam": "Nott'm Forest",
        "SOT_Conc": 124,
        "G_Conc": 43,
        "SOT_per_Goal": 2.88
      },
      {
        "HomeTeam": "Brentford",
        "SOT_Conc": 118,
        "G_Conc": 42,
        "SOT_per_Goal": 2.81
      },
      {
        "HomeTeam": "Liverpool",
        "SOT_Conc": 111,
        "G_Conc": 40,
        "SOT_per_Goal": 2.78
      },
      {
        "HomeTeam": "Tottenham",
        "SOT_Conc": 128,
        "G_Conc": 47,
        "SOT_per_Goal": 2.72
      },
      {
        "HomeTeam": "Fulham",
        "SOT_Conc": 115,
        "G_Conc": 43,
        "SOT_per_Goal": 2.67
      },
      {
        "HomeTeam": "Wolves",
        "SOT_Conc": 143,
        "G_Conc": 54,
        "SOT_per_Goal": 2.65
      },
      {
        "HomeTeam": "Man United",
        "SOT_Conc": 108,
        "G_Conc": 41,
        "SOT_per_Goal": 2.63
      },
      {
        "HomeTeam": "Leeds",
        "SOT_Conc": 119,
        "G_Conc": 48,
        "SOT_per_Goal": 2.48
      }
    ],
    "17_red_card_survival": [
      {
        "Team": "Chelsea",
        "Total": 7,
        "Win": 1,
        "Draw": 2,
        "Loss": 4,
        "Win%": 14.3,
        "Draw%": 28.6,
        "Loss%": 57.1
      },
      {
        "Team": "Everton",
        "Total": 3,
        "Win": 1,
        "Draw": 1,
        "Loss": 1,
        "Win%": 33.3,
        "Draw%": 33.3,
        "Loss%": 33.3
      },
      {
        "Team": "West Ham",
        "Total": 3,
        "Win": 0,
        "Draw": 0,
        "Loss": 3,
        "Win%": 0.0,
        "Draw%": 0.0,
        "Loss%": 100.0
      },
      {
        "Team": "Wolves",
        "Total": 3,
        "Win": 0,
        "Draw": 0,
        "Loss": 3,
        "Win%": 0.0,
        "Draw%": 0.0,
        "Loss%": 100.0
      },
      {
        "Team": "Newcastle",
        "Total": 2,
        "Win": 1,
        "Draw": 0,
        "Loss": 1,
        "Win%": 50.0,
        "Draw%": 0.0,
        "Loss%": 50.0
      },
      {
        "Team": "Crystal Palace",
        "Total": 2,
        "Win": 0,
        "Draw": 0,
        "Loss": 2,
        "Win%": 0.0,
        "Draw%": 0.0,
        "Loss%": 100.0
      },
      {
        "Team": "Sunderland",
        "Total": 2,
        "Win": 0,
        "Draw": 1,
        "Loss": 1,
        "Win%": 0.0,
        "Draw%": 50.0,
        "Loss%": 50.0
      },
      {
        "Team": "Tottenham",
        "Total": 2,
        "Win": 0,
        "Draw": 0,
        "Loss": 2,
        "Win%": 0.0,
        "Draw%": 0.0,
        "Loss%": 100.0
      },
      {
        "Team": "Man United",
        "Total": 1,
        "Win": 1,
        "Draw": 0,
        "Loss": 0,
        "Win%": 100.0,
        "Draw%": 0.0,
        "Loss%": 0.0
      },
      {
        "Team": "Aston Villa",
        "Total": 1,
        "Win": 0,
        "Draw": 1,
        "Loss": 0,
        "Win%": 0.0,
        "Draw%": 100.0,
        "Loss%": 0.0
      },
      {
        "Team": "Bournemouth",
        "Total": 1,
        "Win": 0,
        "Draw": 0,
        "Loss": 1,
        "Win%": 0.0,
        "Draw%": 0.0,
        "Loss%": 100.0
      },
      {
        "Team": "Burnley",
        "Total": 1,
        "Win": 0,
        "Draw": 0,
        "Loss": 1,
        "Win%": 0.0,
        "Draw%": 0.0,
        "Loss%": 100.0
      },
      {
        "Team": "Leeds",
        "Total": 1,
        "Win": 0,
        "Draw": 1,
        "Loss": 0,
        "Win%": 0.0,
        "Draw%": 100.0,
        "Loss%": 0.0
      },
      {
        "Team": "Liverpool",
        "Total": 1,
        "Win": 0,
        "Draw": 0,
        "Loss": 1,
        "Win%": 0.0,
        "Draw%": 0.0,
        "Loss%": 100.0
      }
    ],
    "18_quick_stats": {
      "home_win_pct": 41.5,
      "avg_goals_per_game": 2.73,
      "most_common_referee": "A Taylor"
    }
  }
}